marine_navigator/__init__.py
marine_navigator/demo_utils.py
marine_navigator/port.py
marine_navigator/tidal_calculator.py
marine_navigator/utils.py
marine_navigator/vessel.py
marine_navigator/data/ports.csv
marine_navigator/data/tide_heights.csv
marine_navigator/data/vessels.csv
marine_navigation-0.4.1.dist-info/LICENSE
marine_navigation-0.4.1.dist-info/METADATA
marine_navigation-0.4.1.dist-info/WHEEL
marine_navigation-0.4.1.dist-info/top_level.txt
marine_navigation-0.4.1.dist-info/RECORD
